{"LeftAttack":{"height":90,"width":156,"className":"LeftAttack","id":"1041","totalFrames":21},"LeftDefend":{"height":52,"width":83,"className":"LeftDefend","id":"1041","totalFrames":2},"LeftDie":{"height":104,"width":110,"className":"LeftDie","id":"1041","totalFrames":19},"LeftHit":{"height":72,"width":77,"className":"LeftHit","id":"1041","totalFrames":3},"LeftMagic":{"height":134,"width":134,"className":"LeftMagic","id":"1041","totalFrames":37},"LeftStand":{"height":53,"width":66,"className":"LeftStand","id":"1041","totalFrames":23},"LeftWalk":{"height":56,"width":63,"className":"LeftWalk","id":"1041","totalFrames":7},"RightAttack":{"height":107,"width":124,"className":"RightAttack","id":"1041","totalFrames":21},"RightDefend":{"height":73,"width":53,"className":"RightDefend","id":"1041","totalFrames":2},"RightDie":{"height":102,"width":90,"className":"RightDie","id":"1041","totalFrames":19},"RightHit":{"height":79,"width":69,"className":"RightHit","id":"1041","totalFrames":5},"RightMagic":{"height":146,"width":100,"className":"RightMagic","id":"1041","totalFrames":37},"RightStand":{"height":53,"width":64,"className":"RightStand","id":"1041","totalFrames":23},"RightWalk":{"height":54,"width":66,"className":"RightWalk","id":"1041","totalFrames":7}}